Metadata-Version: 2.1
Name: sortcl
Version: 2021.3.11.1
Summary: sort multiple angular power spectra in healpy input order
Home-page: https://github.com/ntessore/sortcl
Author: Nicolas Tessore
Author-email: n.tessore@ucl.ac.uk
License: MIT
Project-URL: Documentation, https://cltools.readthedocs.io/sortcl/
Platform: UNKNOWN
Classifier: Programming Language :: Python :: 3
Classifier: License :: OSI Approved :: MIT License
Classifier: Operating System :: OS Independent
Requires-Python: >=3.6
